{
  "routes": [
    {
      "method": "GET",
      "path": "/servicesses",
      "handler": "servicess.find",
      "config": {
        "policies": []
      }
    },
    {
      "method": "GET",
      "path": "/servicesses/count",
      "handler": "servicess.count",
      "config": {
        "policies": []
      }
    },
    {
      "method": "GET",
      "path": "/servicesses/:id",
      "handler": "servicess.findOne",
      "config": {
        "policies": []
      }
    },
    {
      "method": "POST",
      "path": "/servicesses",
      "handler": "servicess.create",
      "config": {
        "policies": []
      }
    },
    {
      "method": "PUT",
      "path": "/servicesses/:id",
      "handler": "servicess.update",
      "config": {
        "policies": []
      }
    },
    {
      "method": "DELETE",
      "path": "/servicesses/:id",
      "handler": "servicess.delete",
      "config": {
        "policies": []
      }
    }
  ]
}
